{"result":"success","data":[{"id":10165412,"contentKey":"10165412_1_90117","contentType":1,"title":"《双点医院》发布全新预告 免费多人联机模式上线","titleStyle":"","smallTitle":"《双点医院》全新预告多人合作上线","imgTitle":"《双点医院》全新预告多人合作上线","hasImgPath":0,"imgPath":"","contentFirstImg":"http://i.17173cdn.com/2fhnvk/YWxqaGBf/cms3/pgiculbnivksznu.jpg!a-3-540x.jpg","originType":null,"origin":"17173整理报道","originUrl":"","author":"王小扣","keywords":"双点医院,多人联机","keywordsList":null,"description":"《双点医院》（Two Point Hospital）是一款恶搞类型的模拟经营游戏，由Two Point Studios制作SEGA发行，游戏将加入全新的多人联机功能。","gameCodes":"10000010090809","gameCodesList":null,"oldGameCodes":"1020016","oldGameCodesList":null,"tags":"双点医院,多人联机","tagsList":null,"weight":0,"weightSet":0,"status":1,"copyrightInfo":"17173.com发布此文仅为传递信息，不代表17173.com认同其观点或证实其描述。","publishTime":1555492805000,"updateTime":null,"createTime":null,"createUserId":90892,"hitCount":null,"supportCount":null,"opposeCount":null,"updateUserId":0,"releaseUserId":90892,"plugin":null,"relateList":null,"shiftTitle":null,"pageUrl":"http://newgame.17173.com/content/04172019/172005077.shtml","categoryId":201129,"defaultCategory":201129,"categoryIds":"201129","categoryIdsList":null,"categoryName":"新闻更新手记","categoryUrl":"http://newgame.17173.com/game-newslist.html","domainId":null,"channelId":206,"channelCode":90117,"channelName":null,"channelUrl":null,"contentText":null,"imageGroupValue":null,"content":null,"hasComment":1,"hasImage":1,"hasVedio":1,"imageList":["http://i.17173cdn.com/2fhnvk/YWxqaGBf/cms3/pgiculbnivksznu.jpg!a-3-540x.jpg","http://i.17173cdn.com/2fhnvk/YWxqaGBf/cms3/MEaBzobnivkszol.jpg!a-3-540x.jpg","http://i.17173cdn.com/2fhnvk/YWxqaGBf/cms3/GISYjKbnivkszoo.jpg!a-3-540x.jpg","http://i.17173cdn.com/2fhnvk/YWxqaGBf/cms3/zkmNdQbnivkszoq.jpg!a-3-540x.jpg","http://i.17173cdn.com/2fhnvk/YWxqaGBf/cms3/ldeiWzbnivkszmp.jpg!a-3-540x.jpg"],"videoList":["//f.v.17173cdn.com/player_f2/Mzg5MjIzNzQ.swf"],"extension1":null,"extension2":null,"extension3":null,"extension4":null,"extension5":null},{"id":10165411,"contentKey":"10165411_1_90117","contentType":1,"title":"《伊苏：塞尔塞塔的树海改》首支宣传片 5月16日发售","titleStyle":"","smallTitle":"《伊苏：塞尔塞塔的树海改》首支宣传片","imgTitle":"《伊苏：塞尔塞塔的树海改》首支宣传片","hasImgPath":0,"imgPath":"","contentFirstImg":"http://i.17173cdn.com/2fhnvk/YWxqaGBf/cms3/dOmxrEbnivjqphe.jpg!a-3-540x.jpg","originType":null,"origin":"17173整理报道","originUrl":"","author":"王小扣","keywords":"伊苏：塞尔塞塔的树海,伊苏宣传片","keywordsList":null,"description":"Falcom今天公布了PS4游戏《伊苏：塞尔塞塔的树海 改》的首支预告片，整体和原版OP基本保持一致，亚特鲁、莉莎、康丽丽卡等角色悉数登场。","gameCodes":"10090010096175","gameCodesList":null,"oldGameCodes":"1028711","oldGameCodesList":null,"tags":"伊苏：塞尔塞塔的树海,伊苏宣传片","tagsList":null,"weight":0,"weightSet":0,"status":1,"copyrightInfo":"17173.com发布此文仅为传递信息，不代表17173.com认同其观点或证实其描述。","publishTime":1555491909000,"updateTime":null,"createTime":null,"createUserId":90892,"hitCount":null,"supportCount":null,"opposeCount":null,"updateUserId":0,"releaseUserId":90892,"plugin":null,"relateList":null,"shiftTitle":null,"pageUrl":"http://newgame.17173.com/content/04172019/170509196.shtml","categoryId":201129,"defaultCategory":201129,"categoryIds":"201129","categoryIdsList":null,"categoryName":"新闻更新手记","categoryUrl":"http://newgame.17173.com/game-newslist.html","domainId":null,"channelId":206,"channelCode":90117,"channelName":null,"channelUrl":null,"contentText":null,"imageGroupValue":null,"content":null,"hasComment":1,"hasImage":1,"hasVedio":1,"imageList":["http://i.17173cdn.com/2fhnvk/YWxqaGBf/cms3/dOmxrEbnivjqphe.jpg!a-3-540x.jpg","http://i.17173cdn.com/2fhnvk/YWxqaGBf/cms3/jkYbzCbnivjqpgy.jpg!a-3-540x.jpg","http://i.17173cdn.com/2fhnvk/YWxqaGBf/cms3/ngpirbbnivjqphn.jpg!a-3-540x.jpg","http://i.17173cdn.com/2fhnvk/YWxqaGBf/cms3/vyxAIibnivjqpiu.jpg!a-3-540x.jpg","http://i.17173cdn.com/2fhnvk/YWxqaGBf/cms3/DCMEjPbnivjqpic.jpg!a-3-540x.jpg","http://i.17173cdn.com/2fhnvk/YWxqaGBf/cms3/MzKialbnivjqphp.jpg!a-3-540x.jpg","http://i.17173cdn.com/2fhnvk/YWxqaGBf/cms3/UyyVnpbnivjqphB.jpg!a-3-540x.jpg","http://i.17173cdn.com/2fhnvk/YWxqaGBf/cms3/PQyrcsbnivjqphw.jpg!a-3-540x.jpg"],"videoList":["//f.v.17173cdn.com/player_f2/Mzg5MjIzNzI.swf"],"extension1":null,"extension2":null,"extension3":null,"extension4":null,"extension5":null},{"id":10165407,"contentKey":"10165407_1_90117","contentType":1,"title":"国产PSVR《除夕：双鱼玉佩》上架PS港服 售价约127元","titleStyle":"","smallTitle":"国产PSVR《除夕：双鱼玉佩》上架PS","imgTitle":"国产PSVR《除夕：双鱼玉佩》上架PS","hasImgPath":0,"imgPath":"","contentFirstImg":"http://i.17173cdn.com/2fhnvk/YWxqaGBf/cms3/zGCDbzbnivitjml.jpg!a-3-540x.jpg","originType":null,"origin":"17173整理报道","originUrl":"","author":"王小扣","keywords":"除夕：双鱼玉佩,国产PSVR","keywordsList":null,"description":"SIEH 在今天宣布，由万岁游戏开发的《除夕：双鱼玉佩》将在4月17日登陆港服PS Store商城，售价为148港币。","gameCodes":"10090010090606","gameCodesList":null,"oldGameCodes":"1024348","oldGameCodesList":null,"tags":"除夕：双鱼玉佩,国产PSVR","tagsList":null,"weight":0,"weightSet":0,"status":1,"copyrightInfo":"17173.com发布此文仅为传递信息，不代表17173.com认同其观点或证实其描述。","publishTime":1555491363000,"updateTime":null,"createTime":null,"createUserId":90892,"hitCount":null,"supportCount":null,"opposeCount":null,"updateUserId":0,"releaseUserId":90892,"plugin":null,"relateList":null,"shiftTitle":null,"pageUrl":"http://newgame.17173.com/content/04172019/165603669.shtml","categoryId":201129,"defaultCategory":201129,"categoryIds":"201129","categoryIdsList":null,"categoryName":"新闻更新手记","categoryUrl":"http://newgame.17173.com/game-newslist.html","domainId":null,"channelId":206,"channelCode":90117,"channelName":null,"channelUrl":null,"contentText":null,"imageGroupValue":null,"content":null,"hasComment":1,"hasImage":1,"hasVedio":0,"imageList":["http://i.17173cdn.com/2fhnvk/YWxqaGBf/cms3/zGCDbzbnivitjml.jpg!a-3-540x.jpg","http://i.17173cdn.com/2fhnvk/YWxqaGBf/cms3/huAxXAbnivitjny.png!a-3-540x.png","http://i.17173cdn.com/2fhnvk/YWxqaGBf/cms3/LtXKidbnivitjlz.jpg!a-3-540x.jpg","http://i.17173cdn.com/2fhnvk/YWxqaGBf/cms3/JOmcfpbnivitjlz.jpg!a-3-540x.jpg","http://i.17173cdn.com/2fhnvk/YWxqaGBf/cms3/jmzTkabnivitjnb.jpg!a-3-540x.jpg","http://i.17173cdn.com/2fhnvk/YWxqaGBf/cms3/UMIfbGbnivitjmA.jpg!a-3-540x.jpg","http://i.17173cdn.com/2fhnvk/YWxqaGBf/cms3/KnozHTbnivitjmc.jpg!a-3-540x.jpg"],"videoList":null,"extension1":null,"extension2":null,"extension3":null,"extension4":null,"extension5":null},{"id":10165406,"contentKey":"10165406_1_90117","contentType":1,"title":"《僵尸世界大战》上架PS4、Xbox One港服商店","titleStyle":"","smallTitle":"《僵尸世界大战》上架PS4、Xbox One港服商店","imgTitle":"《僵尸世界大战》上架PS4、Xbox One港服商店","hasImgPath":0,"imgPath":"","contentFirstImg":"http://i.17173cdn.com/2fhnvk/YWxqaGBf/cms3/dJMPdCbnivicqfk.jpg!a-3-540x.jpg","originType":null,"origin":"17173整理报道","originUrl":"","author":"王小扣","keywords":"","keywordsList":null,"description":"今日，PS4和Xbox One港服商店正式上架了射击游戏《僵尸世界大战》，游戏在两个平台分别售价298港元和299港元，约合人民币255元。","gameCodes":"10000010089933,10090010089933,10100010089933","gameCodesList":null,"oldGameCodes":"1019658","oldGameCodesList":null,"tags":"","tagsList":null,"weight":0,"weightSet":0,"status":1,"copyrightInfo":"17173.com发布此文仅为传递信息，不代表17173.com认同其观点或证实其描述。","publishTime":1555490928000,"updateTime":null,"createTime":null,"createUserId":90892,"hitCount":null,"supportCount":null,"opposeCount":null,"updateUserId":0,"releaseUserId":90892,"plugin":null,"relateList":null,"shiftTitle":null,"pageUrl":"http://newgame.17173.com/content/04172019/164848271.shtml","categoryId":201129,"defaultCategory":201129,"categoryIds":"201129","categoryIdsList":null,"categoryName":"新闻更新手记","categoryUrl":"http://newgame.17173.com/game-newslist.html","domainId":null,"channelId":206,"channelCode":90117,"channelName":null,"channelUrl":null,"contentText":null,"imageGroupValue":null,"content":null,"hasComment":1,"hasImage":1,"hasVedio":0,"imageList":["http://i.17173cdn.com/2fhnvk/YWxqaGBf/cms3/dJMPdCbnivicqfk.jpg!a-3-540x.jpg","http://i.17173cdn.com/2fhnvk/YWxqaGBf/cms3/XPoOjQbnivicqdf.jpg!a-3-540x.jpg","http://i.17173cdn.com/2fhnvk/YWxqaGBf/cms3/lOTIjDbnivicqde.jpg!a-3-540x.jpg","http://i.17173cdn.com/2fhnvk/YWxqaGBf/cms3/KMajmHbnivicqee.jpg!a-3-540x.jpg","http://i.17173cdn.com/2fhnvk/YWxqaGBf/cms3/IVlNOCbnivicqee.jpg!a-3-540x.jpg"],"videoList":null,"extension1":null,"extension2":null,"extension3":null,"extension4":null,"extension5":null},{"id":10165410,"contentKey":"10165410_1_90117","contentType":1,"title":"《我的世界》电影将在2022年3月4日上映，由真人演出","titleStyle":"","smallTitle":"《我的世界》电影将映","imgTitle":"《我的世界》电影将映","hasImgPath":1,"imgPath":"http://i.17173cdn.com/0561y4/YWxqaGBf/gamebase/screenshot/zhmqXGbmChalnAB.png","contentFirstImg":"//i.17173cdn.com/2fhnvk/YWxqaGBf/cms3/aaWfAybmtCEgnqk.jpg!a-3-540x.jpg","originType":null,"origin":"原创","originUrl":"","author":"新游酱","keywords":"我的世界,华纳兄弟","keywordsList":null,"description":"《我的世界》电影将在2022年3月4日上映，由真人演出。","gameCodes":"10002010009999,10022010009999,10032010009999,10232010009999","gameCodesList":null,"oldGameCodes":"1000025","oldGameCodesList":null,"tags":"我的世界,华纳兄弟","tagsList":null,"weight":0,"weightSet":0,"status":1,"copyrightInfo":"17173.com发布此文仅为传递信息，不代表17173.com认同其观点或证实其描述。","publishTime":1555490138000,"updateTime":null,"createTime":null,"createUserId":91832,"hitCount":null,"supportCount":null,"opposeCount":null,"updateUserId":0,"releaseUserId":91832,"plugin":null,"relateList":null,"shiftTitle":null,"pageUrl":"http://newgame.17173.com/content/04172019/163538676.shtml","categoryId":262110,"defaultCategory":262110,"categoryIds":"262110,201129","categoryIdsList":null,"categoryName":"移动大首页推荐分类","categoryUrl":"","domainId":null,"channelId":206,"channelCode":90117,"channelName":null,"channelUrl":null,"contentText":null,"imageGroupValue":null,"content":null,"hasComment":1,"hasImage":1,"hasVedio":0,"imageList":["//i.17173cdn.com/2fhnvk/YWxqaGBf/cms3/aaWfAybmtCEgnqk.jpg!a-3-540x.jpg","//i.17173cdn.com/2fhnvk/YWxqaGBf/cms3/uaydSFbniviBmmf.jpg!a-3-540x.jpg","//i.17173cdn.com/2fhnvk/YWxqaGBf/cms3/aaEFBjbniviECFr.png!a-3-540x.jpg","//i.17173cdn.com/2fhnvk/YWxqaGBf/cms3/yssqEGbniviEFfw.jpg!a-3-540x.jpg"],"videoList":null,"extension1":null,"extension2":null,"extension3":null,"extension4":null,"extension5":null},{"id":10165405,"contentKey":"10165405_1_90117","contentType":1,"title":"4大追加角色也可玩《街霸5》4月24日上线免费体验版","titleStyle":"","smallTitle":"《街霸5》4月24日上线免费体验版 共20名角色都可畅玩","imgTitle":"","hasImgPath":0,"imgPath":"","contentFirstImg":"http://i.17173cdn.com/2fhnvk/YWxqaGBf/cms3/SOgRuhbniveFEdw.jpg","originType":null,"origin":"17173整理报道","originUrl":"","author":"卡索猪猪","keywords":"街霸5","keywordsList":null,"description":"人气格斗游戏《街头霸王5 街机版》((PC / PS4)将于4月24日～5月6日期间上线免费试玩版","gameCodes":"10000010071486","gameCodesList":null,"oldGameCodes":"1014881","oldGameCodesList":null,"tags":"街霸5","tagsList":null,"weight":0,"weightSet":0,"status":1,"copyrightInfo":"17173.com发布此文仅为传递信息，不代表17173.com认同其观点或证实其描述。","publishTime":1555487802000,"updateTime":null,"createTime":null,"createUserId":91297,"hitCount":null,"supportCount":null,"opposeCount":null,"updateUserId":0,"releaseUserId":91297,"plugin":null,"relateList":null,"shiftTitle":null,"pageUrl":"http://newgame.17173.com/content/04172019/155642554.shtml","categoryId":201129,"defaultCategory":201129,"categoryIds":"201129","categoryIdsList":null,"categoryName":"新闻更新手记","categoryUrl":"http://newgame.17173.com/game-newslist.html","domainId":null,"channelId":206,"channelCode":90117,"channelName":null,"channelUrl":null,"contentText":null,"imageGroupValue":null,"content":null,"hasComment":1,"hasImage":1,"hasVedio":0,"imageList":["http://i.17173cdn.com/2fhnvk/YWxqaGBf/cms3/SOgRuhbniveFEdw.jpg","http://i.17173cdn.com/2fhnvk/YWxqaGBf/cms3/BkBRKcbniveFEcd.jpg!a-3-540x.jpg","http://i.17173cdn.com/2fhnvk/YWxqaGBf/cms3/NATVEKbniveFEdy.jpg!a-3-540x.jpg","http://i.17173cdn.com/2fhnvk/YWxqaGBf/cms3/HJgGelbniveFEch.jpg!a-3-540x.jpg","http://i.17173cdn.com/2fhnvk/YWxqaGBf/cms3/XjyijHbniveFEff.jpg!a-3-540x.jpg","http://i.17173cdn.com/2fhnvk/YWxqaGBf/cms3/FOcuiTbniveFEez.jpg!a-3-540x.jpg"],"videoList":null,"extension1":null,"extension2":null,"extension3":null,"extension4":null,"extension5":null},{"id":10165402,"contentKey":"10165402_1_90117","contentType":1,"title":"索尼确认严格监管PS4大尺度内容 引部分开发者不满","titleStyle":"","smallTitle":"索尼确认严格监管PS4大尺度内容","imgTitle":"索尼确认严格监管PS4大尺度内容","hasImgPath":1,"imgPath":"//i.17173cdn.com/2fhnvk/YWxqaGBf/cms3/mvxHRCbnivdDvEw.jpg","contentFirstImg":"//i.17173cdn.com/2fhnvk/YWxqaGBf/cms3/hBowoCbnivdDvED.jpg!a-3-540x.jpg","originType":null,"origin":"转载","originUrl":"游民星空","author":"Jon Fingas","keywords":"索尼,ps4","keywordsList":null,"description":"索尼的这项政策虽然能维护自身的公司形象，但也有可能会让强调开放性的游戏开发者忍痛割爱，为了保证完整体验而转向PC、Switch和Xbox One平台上。","gameCodes":"10131010003195,10131010003496,10000010095559,10000010093055,10000010089962,10090010089962,10100010089962","gameCodesList":null,"oldGameCodes":"1022814,1023028,1028144,1025849,1019675","oldGameCodesList":null,"tags":"索尼,ps4","tagsList":null,"weight":0,"weightSet":0,"status":1,"copyrightInfo":"17173.com发布此文仅为传递信息，不代表17173.com认同其观点或证实其描述。","publishTime":1555486650000,"updateTime":null,"createTime":null,"createUserId":91832,"hitCount":null,"supportCount":null,"opposeCount":null,"updateUserId":0,"releaseUserId":91832,"plugin":null,"relateList":null,"shiftTitle":null,"pageUrl":"http://newgame.17173.com/content/04172019/153730021.shtml","categoryId":262110,"defaultCategory":262110,"categoryIds":"262110,201129","categoryIdsList":null,"categoryName":"移动大首页推荐分类","categoryUrl":"","domainId":null,"channelId":206,"channelCode":90117,"channelName":null,"channelUrl":null,"contentText":null,"imageGroupValue":null,"content":null,"hasComment":1,"hasImage":1,"hasVedio":0,"imageList":["//i.17173cdn.com/2fhnvk/YWxqaGBf/cms3/hBowoCbnivdDvED.jpg!a-3-540x.jpg","//i.17173cdn.com/2fhnvk/YWxqaGBf/cms3/jNmwmgbnivdDvEi.jpg!a-3-540x.jpg","//i.17173cdn.com/2fhnvk/YWxqaGBf/cms3/mvxHRCbnivdDvEw.jpg!a-3-540x.jpg"],"videoList":null,"extension1":null,"extension2":null,"extension3":null,"extension4":null,"extension5":null},{"id":10165390,"contentKey":"10165390_1_90117","contentType":1,"title":"绅士JRPG《死亡终结re;Quest》PC版5月登陆Steam","titleStyle":"","smallTitle":"绅士JRPG《死亡终结re;Quest》PC版5月登陆Steam","imgTitle":"","hasImgPath":0,"imgPath":"","contentFirstImg":"http://i.17173cdn.com/2fhnvk/YWxqaGBf/cms3/JNzbLSbniuwCdkF.jpg!a-3-540x.jpg","originType":null,"origin":"17173整理报道","originUrl":"","author":"卡索猪猪","keywords":"死亡终结re","keywordsList":null,"description":"是一款绅士福利JRPG游戏。该作已经在Steam商店开放了页面，自带中文。","gameCodes":"","gameCodesList":null,"oldGameCodes":null,"oldGameCodesList":null,"tags":"死亡终结re","tagsList":null,"weight":0,"weightSet":0,"status":1,"copyrightInfo":"17173.com发布此文仅为传递信息，不代表17173.com认同其观点或证实其描述。","publishTime":1555473190000,"updateTime":null,"createTime":null,"createUserId":91297,"hitCount":null,"supportCount":null,"opposeCount":null,"updateUserId":91297,"releaseUserId":91297,"plugin":null,"relateList":null,"shiftTitle":null,"pageUrl":"http://newgame.17173.com/content/04172019/115310321.shtml","categoryId":201129,"defaultCategory":201129,"categoryIds":"201129","categoryIdsList":null,"categoryName":"新闻更新手记","categoryUrl":"http://newgame.17173.com/game-newslist.html","domainId":null,"channelId":206,"channelCode":90117,"channelName":null,"channelUrl":null,"contentText":null,"imageGroupValue":null,"content":null,"hasComment":1,"hasImage":1,"hasVedio":1,"imageList":["http://i.17173cdn.com/2fhnvk/YWxqaGBf/cms3/JNzbLSbniuwCdkF.jpg!a-3-540x.jpg","//i.17173cdn.com/2fhnvk/YWxqaGBf/cms3/DnrCQgbniuwDrFz.jpg","http://i.17173cdn.com/2fhnvk/YWxqaGBf/cms3/bsnlzvbniuwCdlb.jpg!a-3-540x.jpg","http://i.17173cdn.com/2fhnvk/YWxqaGBf/cms3/bYheEJbniuwCdko.jpg!a-3-540x.jpg"],"videoList":["//f.v.17173cdn.com/player_f2/Mzg5MjIzMzQ.swf"],"extension1":null,"extension2":null,"extension3":null,"extension4":null,"extension5":null},{"id":10165389,"contentKey":"10165389_1_90117","contentType":1,"title":"《刺客信条：奥德赛》故事线《亚特兰蒂斯之命运》首个章节4月23日发布，美术震撼眼界","titleStyle":"","smallTitle":"《刺客信条：奥德赛》新DLC","imgTitle":"《刺客信条：奥德赛》新DLC","hasImgPath":1,"imgPath":"//i.17173cdn.com/2fhnvk/YWxqaGBf/cms3/IOgITdbniuvACpe.jpg","contentFirstImg":"//i.17173cdn.com/2fhnvk/YWxqaGBf/cms3/IOgITdbniuvACpe.jpg!a-3-540x.jpg","originType":null,"origin":"转载","originUrl":"育碧","author":"育碧游戏","keywords":"刺客信条：奥德赛","keywordsList":null,"description":"育碧宣布《刺客信条：奥德赛》后续更新的第二个故事线《亚特兰蒂斯之命运》的首个章节《至乐之原》将于4月23日在全平台正式发布。","gameCodes":"10000010089892,10090010089892,10100010089892,10230010089892","gameCodesList":null,"oldGameCodes":"1019624,1019624,1019624,1019624","oldGameCodesList":null,"tags":"刺客信条：奥德赛","tagsList":null,"weight":0,"weightSet":0,"status":1,"copyrightInfo":"17173.com发布此文仅为传递信息，不代表17173.com认同其观点或证实其描述。","publishTime":1555471494000,"updateTime":null,"createTime":null,"createUserId":91832,"hitCount":null,"supportCount":null,"opposeCount":null,"updateUserId":91832,"releaseUserId":91832,"plugin":null,"relateList":null,"shiftTitle":null,"pageUrl":"http://newgame.17173.com/content/04172019/112454067.shtml","categoryId":261305,"defaultCategory":261305,"categoryIds":"261305,262110,253388,201129","categoryIdsList":null,"categoryName":"新游推荐","categoryUrl":"http://newgame.17173.com/list/xytj.shtml","domainId":null,"channelId":206,"channelCode":90117,"channelName":null,"channelUrl":null,"contentText":null,"imageGroupValue":null,"content":null,"hasComment":1,"hasImage":1,"hasVedio":1,"imageList":["//i.17173cdn.com/2fhnvk/YWxqaGBf/cms3/IOgITdbniuvACpe.jpg!a-3-540x.jpg","//i.17173cdn.com/2fhnvk/YWxqaGBf/cms3/vzSlXGbniuvACpm.jpg!a-3-540x.jpg","//i.17173cdn.com/2fhnvk/YWxqaGBf/cms3/RLrpWRbniuvACrg.jpg!a-3-540x.jpg"],"videoList":["//f.v.17173cdn.com/player_f2/Mzg5MjIzMzM.swf"],"extension1":null,"extension2":null,"extension3":null,"extension4":null,"extension5":null},{"id":10165387,"contentKey":"10165387_1_90117","contentType":1,"title":"“PS5”最新情报公布，支持对PS4的向下兼容，不会在2019年发售","titleStyle":"","smallTitle":"“PS5”最新情报","imgTitle":"“PS5”最新情报","hasImgPath":1,"imgPath":"//i.17173cdn.com/2fhnvk/YWxqaGBf/cms3/qWbxDcbniutbBzc.jpg","contentFirstImg":"//i.17173cdn.com/2fhnvk/YWxqaGBf/cms3/uHESTPbniutaAil.jpg!a-3-480x.jpg","originType":null,"origin":"原创","originUrl":"","author":"新游酱","keywords":"PS5,ps4,索尼","keywordsList":null,"description":"“PS5”的最新情报。","gameCodes":"10090010090027","gameCodesList":null,"oldGameCodes":"1019714","oldGameCodesList":null,"tags":"PS5,ps4,索尼,PS5,ps4,索尼,PS5,ps4,索尼","tagsList":null,"weight":0,"weightSet":0,"status":1,"copyrightInfo":"17173.com发布此文仅为传递信息，不代表17173.com认同其观点或证实其描述。","publishTime":1555468281000,"updateTime":null,"createTime":null,"createUserId":91832,"hitCount":null,"supportCount":null,"opposeCount":null,"updateUserId":91832,"releaseUserId":91832,"plugin":null,"relateList":null,"shiftTitle":null,"pageUrl":"http://newgame.17173.com/content/04172019/103121745.shtml","categoryId":262110,"defaultCategory":262110,"categoryIds":"262110,201129","categoryIdsList":null,"categoryName":"移动大首页推荐分类","categoryUrl":"","domainId":null,"channelId":206,"channelCode":90117,"channelName":null,"channelUrl":null,"contentText":null,"imageGroupValue":null,"content":null,"hasComment":1,"hasImage":1,"hasVedio":0,"imageList":["//i.17173cdn.com/2fhnvk/YWxqaGBf/cms3/uHESTPbniutaAil.jpg!a-3-480x.jpg","//i.17173cdn.com/2fhnvk/YWxqaGBf/cms3/qWbxDcbniutbBzc.jpg!a-3-540x.jpg","//i.17173cdn.com/2fhnvk/YWxqaGBf/cms3/qUMhHSbniutbBzp.jpg!a-3-540x.jpg","//i.17173cdn.com/2fhnvk/YWxqaGBf/cms3/nDePpKbniutbByA.jpg!a-3-540x.jpg","//i.17173cdn.com/2fhnvk/YWxqaGBf/cms3/KwnUUzbniutbBzk.jpg!a-3-540x.jpg"],"videoList":null,"extension1":null,"extension2":null,"extension3":null,"extension4":null,"extension5":null}],"status":1,"totalCount":13463}